whatif/__init__.py
whatif/sample.py
whatif-0.0.0.dist-info/entry_points.txt
whatif-0.0.0.dist-info/WHEEL
whatif-0.0.0.dist-info/METADATA
whatif-0.0.0.dist-info/RECORD
